exomole/__init__.py
exomole/exceptions.py
exomole/read_all.py
exomole/read_data.py
exomole/read_def.py
exomole/utils.py
exomole-1.2.12.dist-info/LICENSE
exomole-1.2.12.dist-info/METADATA
exomole-1.2.12.dist-info/WHEEL
exomole-1.2.12.dist-info/top_level.txt
exomole-1.2.12.dist-info/RECORD
