Metadata-Version: 2.1
Name: exomole
Version: 1.2.12
Summary: A package for parsing and validation of Exomol Database data files
Home-page: https://github.com/hanicinecm/exomole/
Author: Martin Hanicinec
Author-email: hanicinecm@gmail.com
License: UNKNOWN
Project-URL: Bug Reports, https://github.com/hanicinecm/exomole/issues
Project-URL: Documentation, https://github.com/hanicinecm/exomole/tree/master/docs/index.rst
Keywords: exomol
Platform: UNKNOWN
Classifier: Development Status :: 4 - Beta
Classifier: Intended Audience :: Science/Research
Classifier: Topic :: Scientific/Engineering :: Astronomy
Classifier: License :: OSI Approved :: MIT License
Classifier: Programming Language :: Python :: 3
Classifier: Programming Language :: Python :: 3.6
Classifier: Programming Language :: Python :: 3.7
Classifier: Programming Language :: Python :: 3.8
Classifier: Programming Language :: Python :: 3.9
Classifier: Programming Language :: Python :: 3.10
Classifier: Programming Language :: Python :: 3 :: Only
Classifier: Operating System :: OS Independent
Requires-Python: >=3.6
License-File: LICENSE
Requires-Dist: pandas
Requires-Dist: requests
Requires-Dist: pyvalem (>=2.3)
Provides-Extra: dev
Requires-Dist: pytest-cov ; extra == 'dev'
Requires-Dist: tox ; extra == 'dev'
Requires-Dist: black ; extra == 'dev'
Requires-Dist: ipython ; extra == 'dev'
